EMToolKit/EMToolKit.py
EMToolKit/__init__.py
EMToolKit/examples.py
EMToolKit/util.py
EMToolKit/algorithms/__init__.py
EMToolKit/algorithms/multi_inst_dem_wrapper.py
EMToolKit/algorithms/simple_reg_dem.py
EMToolKit/algorithms/simple_reg_dem_parallel.py
EMToolKit/algorithms/simple_reg_dem_wrapper.py
EMToolKit/algorithms/simple_reg_dem_wrapper_parallel.py
EMToolKit/algorithms/sparse_em.py
EMToolKit/algorithms/sparse_em_wrapper.py
EMToolKit/algorithms/sparse_nlmap_dem_wrapper.py
EMToolKit/algorithms/sparse_nlmap_solver.py
EMToolKit/instruments/__init__.py
EMToolKit/instruments/aia.py
EMToolKit/instruments/xrt.py
EMToolKit/schemas/__init__.py
EMToolKit/schemas/basic_schemas.py
EMToolKit/schemas/basic_transforms.py
EMToolKit/schemas/coord_grid.py
EMToolKit/schemas/element_functions.py
EMToolKit/schemas/element_grid.py
EMToolKit/schemas/element_source_responses.py
EMToolKit/schemas/operators.py
EMToolKit/schemas/util.py
EMToolKit/visualization/__init__.py
EMToolKit/visualization/dashboard.py
EMToolKit/visualization/testing.ipynb
emtoolkit-0.1.11.dist-info/METADATA
emtoolkit-0.1.11.dist-info/WHEEL
emtoolkit-0.1.11.dist-info/entry_points.txt
emtoolkit-0.1.11.dist-info/licenses/LICENSE
emtoolkit-0.1.11.dist-info/RECORD
